utnamgeo/__init__.py
utnamgeo-0.0.3.dist-info/LICENCE.txt
utnamgeo-0.0.3.dist-info/METADATA
utnamgeo-0.0.3.dist-info/WHEEL
utnamgeo-0.0.3.dist-info/top_level.txt
utnamgeo-0.0.3.dist-info/RECORD
