Metadata-Version: 2.1
Name: utnamgeo
Version: 0.0.3
Summary: Python library for 2d/3d coordinate geometry
Home-page: https://github.com/utkarsh-naman/utnamgeo
Author: Utkarsh Naman
Author-email: its.utnam@gmail.com
License: MIT
Keywords: cogeo geometry coordinate-geometry math evaluate calculate
Platform: UNKNOWN
Classifier: Development Status :: 5 - Production/Stable
Classifier: Intended Audience :: Education
Classifier: Operating System :: POSIX :: Linux
Classifier: License :: OSI Approved :: MIT License
Classifier: Programming Language :: Python :: 2.7
Classifier: Programming Language :: Python :: 3
License-File: LICENCE.txt
Requires-Dist: utnamtte
